effcossim
