Metadata-Version: 2.1
Name: effcossim
Version: 1.0.4
Summary: Efficient Pairwise Cosine Similarity Computation
Home-page: https://github.com/ngshya/effcossim
Author: ngshya
Author-email: ngshya@gmail.com
License: GPLv3
Platform: UNKNOWN
